LiveTune/LiveVariableBase.py
LiveTune/__init__.py
LiveTune/liveTrigger.py
LiveTune/liveVar.py
LiveTune/tools/__init__.py
LiveTune/tools/tune.py
LiveTune-0.0.8.dist-info/LICENSE
LiveTune-0.0.8.dist-info/METADATA
LiveTune-0.0.8.dist-info/WHEEL
LiveTune-0.0.8.dist-info/entry_points.txt
LiveTune-0.0.8.dist-info/top_level.txt
LiveTune-0.0.8.dist-info/RECORD
