Metadata-Version: 2.1
Name: LiveTune
Version: 0.0.8
Summary: Python package for ML developers and researchers to change certain variables while their code is executing to make the task of training a ML project easier. This package will allow you to tune some parameters while your code is live from outside of the program.
Home-page: https://github.com/soheilzi/LiveTune
Author: Soheil Zibakhsh Shabgahi, Aiden Tabrizi
Author-email: szibakhshshabgahi@ucsd.edu, atabrizi@ucsd.edu
Classifier: Programming Language :: Python :: 3
Classifier: License :: Other/Proprietary License
Classifier: Operating System :: OS Independent
Requires-Python: >=3.7
License-File: LICENSE
